carve/__init__.py
carve/__version__.py
carve/carve.py
carve/curried.py
carve-0.2.1.dist-info/WHEEL
carve-0.2.1.dist-info/METADATA
carve-0.2.1.dist-info/RECORD
